[
    {
        "SaveId": "40b038bd-bd8e-4038-8b60-2688db16d430",
        "UserId": "4453e558-cd4f-41da-b493-a7ecb747d262",
        "PlayerObject": {
            "IsPlayer": true,
            "Level": 1,
            "Experience": 0,
            "Item": {
                "ItemId": "35defdf8-0a2b-4414-9a30-a4f8e3221a4b",
                "SkillIndex": 2,
                "Modifier": 1,
                "Coordinates": {
                    "X": 0,
                    "Y": 0
                }
            },
            "SkillPoints": 2,
            "Skills": [
                1,
                1
            ],
            "AttributePoints": 2,
            "Attributes": [
                1,
                1,
                1
            ],
            "Coordinates": {
                "X": 0,
                "Y": 0
            },
            "CharacterClass": 1
        },
        "SaveDate": "2024-05-16T16:47:51.6461284-04:00",
        "Turns": 25,
        "Units": 2,
        "GridConstraints": {
            "X": 13,
            "Y": 13
        },
        "Tasks": null,
        "Encounters": null,
        "Items": [
            {
                "ItemId": "e8f54b48-3d8b-4506-9747-c114d0409429",
                "SkillIndex": 0,
                "Modifier": 0,
                "Coordinates": {
                    "X": 2,
                    "Y": -1
                }
            },
            {
                "ItemId": "6ef80575-efcc-4d20-b1db-5dc6fcd4ceb6",
                "SkillIndex": 0,
                "Modifier": 0,
                "Coordinates": {
                    "X": -8,
                    "Y": -9
                }
            },
            {
                "ItemId": "35defdf8-0a2b-4f3a-9a30-a4f8e3221a4b",
                "SkillIndex": 0,
                "Modifier": 0,
                "Coordinates": {
                    "X": -13,
                    "Y": -13
                }
            }
        ]
    }
]